clickplc/__init__.py
clickplc/driver.py
clickplc/mock.py
clickplc/util.py
clickplc-0.14.0.dist-info/licenses/LICENSE
clickplc-0.14.0.dist-info/METADATA
clickplc-0.14.0.dist-info/WHEEL
clickplc-0.14.0.dist-info/entry_points.txt
clickplc-0.14.0.dist-info/top_level.txt
clickplc-0.14.0.dist-info/RECORD
