Metadata-Version: 2.4
Name: clickplc
Version: 0.14.0
Summary: Python driver for AutomationDirect (formerly Koyo) Ethernet ClickPLCs.
Author-email: Pat Fuller <patrickfuller@gmail.com>
Maintainer-email: Alex Ruddick <alex@ruddick.tech>
License-Expression: GPL-2.0-or-later
Project-URL: Homepage, https://github.com/alexrudd2/clickplc
Project-URL: Issues, https://github.com/alexrudd2/clickplc/issues
Classifier: Development Status :: 4 - Beta
Classifier: Natural Language :: English
Classifier: Programming Language :: Python
Classifier: Programming Language :: Python :: 3
Classifier: Programming Language :: Python :: 3.9
Classifier: Programming Language :: Python :: 3.10
Classifier: Programming Language :: Python :: 3.11
Classifier: Programming Language :: Python :: 3.12
Classifier: Programming Language :: Python :: 3.13
Classifier: Programming Language :: Python :: 3.14
Classifier: Topic :: Scientific/Engineering :: Human Machine Interfaces
Classifier: Topic :: Scientific/Engineering :: Electronic Design Automation (EDA)
License-File: LICENSE
Requires-Dist: pymodbus>=2.4.0; python_version == "3.9"
Requires-Dist: pymodbus<3.11.0,>=3.0.2; python_version >= "3.10"
Provides-Extra: test
Requires-Dist: mypy==1.17.1; extra == "test"
Requires-Dist: pytest; extra == "test"
Requires-Dist: pytest-cov; extra == "test"
Requires-Dist: pytest-asyncio>=0.23.8; extra == "test"
Requires-Dist: ruff==0.12.7; extra == "test"
Requires-Dist: types-PyYAML; extra == "test"
Requires-Dist: pyserial-asyncio>=0.4.0; python_version == "3.9" and extra == "test"
Dynamic: license-file
